mcp_jira/__init__.py
mcp_jira/server.py
mcp_jira-0.0.2.dist-info/METADATA
mcp_jira-0.0.2.dist-info/WHEEL
mcp_jira-0.0.2.dist-info/entry_points.txt
mcp_jira-0.0.2.dist-info/top_level.txt
mcp_jira-0.0.2.dist-info/RECORD
