Metadata-Version: 2.4
Name: mcp-jira
Version: 0.0.2
Summary: MCP server for Jira integration
Requires-Python: >=3.10
Requires-Dist: mcp[cli]>=1.6.0
Requires-Dist: httpx>=0.24.0
